apiwatch/__init__.py
apiwatch/__main__.py
apiwatch/changes-log.md
apiwatch/middleware_fastapi.py
apiwatch/middleware_flask.py
apiwatch/server.py
apiwatch/standalone_server.py
apiwatch/watcher.py
apiwatch/ui/__init__.py
apiwatch/ui/index.html
apiwatch/ui/scripts.js
apiwatch/ui/styles.css
apiwatch/ui/template_ui.py
api_watch-0.1.5.dist-info/METADATA
api_watch-0.1.5.dist-info/WHEEL
api_watch-0.1.5.dist-info/top_level.txt
api_watch-0.1.5.dist-info/RECORD
