Metadata-Version: 2.4
Name: api-watch
Version: 0.1.5
Summary: Real-time API monitoring for Flask/FastAPI with async, zero-blocking logging
Home-page: https://github.com/mount-isaac/api-watch
Author: Isaac Kyalo
Author-email: Isaac Kyalo <isadechair019@gmail.com>
License: MIT
Project-URL: Homepage, https://github.com/mount-isaac/api-watch
Project-URL: Documentation, https://github.com/mount-isaac/api-watch#readme
Project-URL: Repository, https://github.com/mount-isaac/api-watch
Project-URL: Bug Tracker, https://github.com/mount-isaac/api-watch/issues
Keywords: api,monitoring,flask,fastapi,logging,debugging,websocket,real-time
Classifier: Development Status :: 3 - Alpha
Classifier: Intended Audience :: Developers
Classifier: Topic :: Software Development :: Libraries :: Python Modules
Classifier: License :: OSI Approved :: MIT License
Classifier: Programming Language :: Python :: 3
Classifier: Programming Language :: Python :: 3.7
Classifier: Programming Language :: Python :: 3.8
Classifier: Programming Language :: Python :: 3.9
Classifier: Programming Language :: Python :: 3.11
Classifier: Programming Language :: Python :: 3.12
Classifier: Programming Language :: Python :: 3.13
Classifier: Framework :: Flask
Classifier: Framework :: FastAPI
Requires-Python: >=3.7
Requires-Dist: aiohttp>=3.8.0
Requires-Dist: aiosqlite>=0.21.0
Provides-Extra: flask
Requires-Dist: flask>=2.0.0; extra == "flask"
Provides-Extra: fastapi
Requires-Dist: fastapi>=0.100.0; extra == "fastapi"
Requires-Dist: uvicorn>=0.23.0; extra == "fastapi"
Provides-Extra: all
Requires-Dist: flask>=2.0.0; extra == "all"
Requires-Dist: fastapi>=0.100.0; extra == "all"
Requires-Dist: uvicorn>=0.23.0; extra == "all"
Provides-Extra: dev
Requires-Dist: pytest>=7.0; extra == "dev"
Requires-Dist: black>=23.0; extra == "dev"
Requires-Dist: flask>=2.0.0; extra == "dev"
Requires-Dist: flake8>=6.0; extra == "dev"
Requires-Dist: fastapi>=0.100.0; extra == "dev"
Requires-Dist: uvicorn>=0.23.0; extra == "dev"
Requires-Dist: mypy>=1.0; extra == "dev"
Requires-Dist: sphinx>=5.0; extra == "dev"
Requires-Dist: sphinx-rtd-theme>=1.0; extra == "dev"
Requires-Dist: myst-parser>=0.18; extra == "dev"
Dynamic: author
Dynamic: home-page
Dynamic: requires-python
